setup.py
dbgap_to_owl/__init__.py
dbgap_to_owl/schema_wrappers.py
dbgap_to_owl.egg-info/PKG-INFO
dbgap_to_owl.egg-info/SOURCES.txt
dbgap_to_owl.egg-info/dependency_links.txt
dbgap_to_owl.egg-info/requires.txt
dbgap_to_owl.egg-info/top_level.txt
scripts/dbgaptoowl